MANIFEST.in
README.rst
setup.cfg
setup.py
ckanext/__init__.py
ckanext/aaf/__init__.py
ckanext/aaf/controller.py
ckanext/aaf/plugin.py
ckanext/aaf/templates/user/new.html
ckanext/aaf/templates/user/snippets/login_form.html
ckanext/aaf/tests/__init__.py
ckanext/aaf/tests/test_plugin.py
ckanext_aaf.egg-info/PKG-INFO
ckanext_aaf.egg-info/SOURCES.txt
ckanext_aaf.egg-info/dependency_links.txt
ckanext_aaf.egg-info/entry_points.txt
ckanext_aaf.egg-info/pbr.json
ckanext_aaf.egg-info/requires.txt
ckanext_aaf.egg-info/top_level.txt