Metadata-Version: 1.1
Name: ckanext-aaf
Version: 0.0.8
Summary: Authentication via AAF Rapid Connect
Home-page: https://github.com/Psykar/ckanext-aaf
Author: Louis des Landes
Author-email: ldeslandes@swin.edu.au
License: AGPL
Keywords: CKAN AAF shibboleth authentication rapid connect
Platform: UNKNOWN
Classifier: Development Status :: 4 - Beta
Classifier: License :: OSI Approved :: GNU Affero General Public License v3 or later (AGPLv3+)
Classifier: Programming Language :: Python :: 2.6
Classifier: Programming Language :: Python :: 2.7
